CHANGELOG.txt
LICENSE.txt
MANIFEST.in
README.txt
setup.py
base/__init__.py
basepage/__init__.py
configfiles/__init__.py
configfiles/config.py
dianafirstcalc.egg-info/PKG-INFO
dianafirstcalc.egg-info/SOURCES.txt
dianafirstcalc.egg-info/dependency_links.txt
dianafirstcalc.egg-info/requires.txt
dianafirstcalc.egg-info/top_level.txt
op1/__init__.py
op2/__init__.py
selenium_driver/__init__.py
utilities/__init__.py
utilities/custom_logger.py
utilities/util.py
webdriverfactory/__init__.py