Metadata-Version: 1.1
Name: dianafirstcalc
Version: 1.0.0
Summary: A very basic calculator
Home-page: UNKNOWN
Author:  Diana Hernandez
Author-email: dianyrob78@gmail.com
License: MIT
Keywords: calculator
Platform: UNKNOWN
Classifier: Development Status :: 5 - Production/Stable
Classifier: Intended Audience :: Education
Classifier: License :: OSI Approved :: MIT License
Classifier: Programming Language :: Python :: 3
